GNavbar/GNavbar.cp310-win_amd64.pyd
GNavbar/__init__.py
GNavbar-1.0.221019.dist-info/METADATA
GNavbar-1.0.221019.dist-info/WHEEL
GNavbar-1.0.221019.dist-info/top_level.txt
GNavbar-1.0.221019.dist-info/RECORD
