Metadata-Version: 2.1
Name: GNavbar
Version: 1.0.221019
Summary: Navigation bar expansion package based on PyQt5 and PySide2.(x64 bit os only)
Home-page: https://laoguobest.com
Author: LAOGUObest
Author-email: LAOGUOszyyds1804@qq.com
Classifier: Programming Language :: Python
Classifier: Programming Language :: Python :: 3.10
